cut_finder.cp311-win_amd64.pyd
d_imm/__init__.py
d_imm/histogram.py
d_imm/imm_model.py
d_imm/histogram/__init__.py
d_imm/histogram/histogram.py
d_imm/histogram/test_main.py
d_imm/splitters/__init__.py
d_imm/splitters/cut_finder.c
d_imm/splitters/cut_finder.pyx
d_imm/splitters/setup.py
splitters/cut_finder.cp311-win_amd64.pyd
distributed_imm_newesttt-0.1.dist-info/METADATA
distributed_imm_newesttt-0.1.dist-info/WHEEL
distributed_imm_newesttt-0.1.dist-info/top_level.txt
distributed_imm_newesttt-0.1.dist-info/RECORD
